imread_benchmark/__init__.py
imread_benchmark/benchmark.py
imread_benchmark-0.0.5.dist-info/LICENSE
imread_benchmark-0.0.5.dist-info/METADATA
imread_benchmark-0.0.5.dist-info/WHEEL
imread_benchmark-0.0.5.dist-info/entry_points.txt
imread_benchmark-0.0.5.dist-info/top_level.txt
imread_benchmark-0.0.5.dist-info/RECORD
