Metadata-Version: 2.1
Name: imread-benchmark
Version: 0.0.5
Summary: Benchmark for image reading for different libraries.
Home-page: https://github.com/ternaus/imread_benchmark
Author: Vladimir Iglovikov
Author-email: iglovikov@gmail.com
License: MIT
Platform: UNKNOWN
Classifier: License :: OSI Approved :: MIT License
Classifier: Intended Audience :: Developers
Classifier: Intended Audience :: Science/Research
Classifier: Operating System :: OS Independent
Classifier: Programming Language :: Python
Classifier: Programming Language :: Python :: 3
Classifier: Topic :: Software Development :: Libraries
Classifier: Topic :: Software Development :: Libraries :: Python Modules
Requires-Dist: black
Requires-Dist: flake8
Requires-Dist: imageio
Requires-Dist: isort
Requires-Dist: jpeg4py
Requires-Dist: numpy
Requires-Dist: opencv-python
Requires-Dist: pandas
Requires-Dist: pillow-simd
Requires-Dist: pytest
Requires-Dist: pyvips
Requires-Dist: scikit-image
Requires-Dist: tqdm
Provides-Extra: test
Requires-Dist: pytest ; extra == 'test'
